jsondb/__init__.py
jsondb/cli.py
jsondb/core.py
jsondb/exceptions.py
jsondb/operations.py
jsondb/repl.py
jsondb/storage.py
jsondb/utils.py
jsondb_python-1.0.9.dist-info/licenses/LICENSE
jsondb_python-1.0.9.dist-info/METADATA
jsondb_python-1.0.9.dist-info/WHEEL
jsondb_python-1.0.9.dist-info/entry_points.txt
jsondb_python-1.0.9.dist-info/top_level.txt
jsondb_python-1.0.9.dist-info/RECORD
