Metadata-Version: 2.4
Name: jsondb-python
Version: 1.0.9
Summary: A simple, lightweight, and file-based JSON database library for Python.
Home-page: https://github.com/Elang-elang/JsonDB
Author: Elang Muhammad
Author-email: Elang Muhammad <elangmuhammad888@gmail.com>
License: MIT License
Project-URL: Homepage, https://github.com/Elang-elang/
Project-URL: Repository, https://github.com/Elang-elang/JsonDB
Project-URL: Issues, https://github.com/Elang-elang/JsonDB/issues
Keywords: json,database,file-based,nosql,db
Classifier: Programming Language :: Python :: 3
Classifier: License :: OSI Approved :: MIT License
Classifier: Operating System :: OS Independent
Classifier: Topic :: Database
Classifier: Intended Audience :: Developers
Classifier: Development Status :: 4 - Beta
Classifier: Programming Language :: Python :: 3.8
Classifier: Programming Language :: Python :: 3.9
Classifier: Programming Language :: Python :: 3.10
Classifier: Programming Language :: Python :: 3.11
Classifier: Programming Language :: Python :: 3.12
Requires-Python: >=3.8
License-File: LICENSE
Requires-Dist: prompt_toolkit
Dynamic: author
Dynamic: home-page
Dynamic: license-file
Dynamic: requires-python
